clusterweb/__init__.py
clusterweb/interfaces/__init__.py
clusterweb/interfaces/ssh.py
clusterweb/interfaces/system.py
clusterweb/interfaces/template.py
clusterweb/local/__init__.py
clusterweb/local/del.py
clusterweb/local/session.py
clusterweb/local/stat.py
clusterweb/local/sub.py
clusterweb/pbs/__init__.py
clusterweb/pbs/cluster_functions.py
clusterweb/pbs/config.py
clusterweb/pbs/qdel.py
clusterweb/pbs/qsession.py
clusterweb/pbs/qstat.py
clusterweb/pbs/qsub.py
clusterweb/pbs/scripts.py
clusterweb-0.0.0.2.dist-info/LICENSE
clusterweb-0.0.0.2.dist-info/METADATA
clusterweb-0.0.0.2.dist-info/WHEEL
clusterweb-0.0.0.2.dist-info/top_level.txt
clusterweb-0.0.0.2.dist-info/RECORD
