Metadata-Version: 2.1
Name: clusterweb
Version: 0.0.0.2
Summary: ClusterWeb, a distributed system API for SSH and PBS systems
Home-page: https://github.com/gndctrl2mjrtm/cweb-project
Author: Stephen Offer
Author-email: offercstephen@example.com
License: MIT
Platform: UNKNOWN
